odoo/addons/intrastat_base/README.rst
odoo/addons/intrastat_base/__init__.py
odoo/addons/intrastat_base/__manifest__.py
odoo/addons/intrastat_base/demo/intrastat_demo.xml
odoo/addons/intrastat_base/i18n/es.po
odoo/addons/intrastat_base/i18n/fr.po
odoo/addons/intrastat_base/i18n/intrastat_base.pot
odoo/addons/intrastat_base/i18n/it.po
odoo/addons/intrastat_base/models/__init__.py
odoo/addons/intrastat_base/models/account_fiscal_position.py
odoo/addons/intrastat_base/models/account_move.py
odoo/addons/intrastat_base/models/product_template.py
odoo/addons/intrastat_base/models/res_company.py
odoo/addons/intrastat_base/readme/CONTRIBUTORS.md
odoo/addons/intrastat_base/readme/DESCRIPTION.md
odoo/addons/intrastat_base/readme/INSTALL.md
odoo/addons/intrastat_base/readme/USAGE.md
odoo/addons/intrastat_base/static/description/icon.png
odoo/addons/intrastat_base/static/description/index.html
odoo/addons/intrastat_base/tests/__init__.py
odoo/addons/intrastat_base/tests/common.py
odoo/addons/intrastat_base/tests/models.py
odoo/addons/intrastat_base/tests/test_all.py
odoo/addons/intrastat_base/views/account_fiscal_position.xml
odoo/addons/intrastat_base/views/intrastat.xml
odoo/addons/intrastat_base/views/product_template.xml
odoo/addons/intrastat_base/views/res_config_settings.xml
odoo/addons/intrastat_base/views/res_partner.xml
odoo/addons/intrastat_base/wizards/__init__.py
odoo/addons/intrastat_base/wizards/res_config_settings.py
odoo_addon_intrastat_base-19.0.1.0.0.2.dist-info/METADATA
odoo_addon_intrastat_base-19.0.1.0.0.2.dist-info/WHEEL
odoo_addon_intrastat_base-19.0.1.0.0.2.dist-info/top_level.txt
odoo_addon_intrastat_base-19.0.1.0.0.2.dist-info/RECORD
