Metadata-Version: 2.1
Name: odoo-addon-intrastat_base
Version: 19.0.1.0.0.2
Requires-Dist: odoo==19.0.*
Summary: Base module for Intrastat reporting
Home-page: https://github.com/OCA/intrastat-extrastat
License: AGPL-3
Author: ACSONE SA/NV,Akretion,Noviat,Odoo Community Association (OCA)
Author-email: support@odoo-community.org
Classifier: Programming Language :: Python
Classifier: Framework :: Odoo
Classifier: Framework :: Odoo :: 19.0
Classifier: License :: OSI Approved :: GNU Affero General Public License v3
